[
  {
    "inputs": [],
    "stateMutability": "nonpayable",
    "type": "constructor"
  },
  {
    "inputs": [
      {
        "internalType": "uint256",
        "name": "",
        "type": "uint256"
      }
    ],
    "name": "activePendingPropertyIds",
    "outputs": [
      {
        "internalType": "uint256",
        "name": "",
        "type": "uint256"
      }
    ],
    "stateMutability": "view",
    "type": "function"
  },
  {
    "inputs": [
      {
        "internalType": "uint256",
        "name": "pendingIndex",
        "type": "uint256"
      }
    ],
    "name": "approveAndTokenizeProperty",
    "outputs": [],
    "stateMutability": "nonpayable",
    "type": "function"
  },
  {
    "inputs": [
      {
        "internalType": "uint256",
        "name": "propertyId",
        "type": "uint256"
      },
      {
        "internalType": "uint256",
        "name": "listingIndex",
        "type": "uint256"
      }
    ],
    "name": "buyFromListing",
    "outputs": [],
    "stateMutability": "payable",
    "type": "function"
  },
  {
    "inputs": [
      {
        "internalType": "uint256",
        "name": "propertyId",
        "type": "uint256"
      },
      {
        "internalType": "uint256",
        "name": "tokenAmount",
        "type": "uint256"
      }
    ],
    "name": "buyFromSale",
    "outputs": [],
    "stateMutability": "payable",
    "type": "function"
  },
  {
    "inputs": [
      {
        "internalType": "uint256",
        "name": "propertyId",
        "type": "uint256"
      },
      {
        "internalType": "uint256",
        "name": "listingIndex",
        "type": "uint256"
      }
    ],
    "name": "cancelListing",
    "outputs": [],
    "stateMutability": "nonpayable",
    "type": "function"
  },
  {
    "inputs": [
      {
        "internalType": "uint256",
        "name": "pendingIndex",
        "type": "uint256"
      }
    ],
    "name": "disapproveProperty",
    "outputs": [],
    "stateMutability": "nonpayable",
    "type": "function"
  },
  {
    "inputs": [
      {
        "internalType": "uint256",
        "name": "propertyId",
        "type": "uint256"
      },
      {
        "internalType": "address",
        "name": "user",
        "type": "address"
      }
    ],
    "name": "getBuyerInfo",
    "outputs": [
      {
        "internalType": "uint256",
        "name": "tokensBought",
        "type": "uint256"
      }
    ],
    "stateMutability": "view",
    "type": "function"
  },
  {
    "inputs": [
      {
        "internalType": "uint256",
        "name": "propertyId",
        "type": "uint256"
      }
    ],
    "name": "getBuyers",
    "outputs": [
      {
        "internalType": "address[]",
        "name": "",
        "type": "address[]"
      }
    ],
    "stateMutability": "view",
    "type": "function"
  },
  {
    "inputs": [
      {
        "internalType": "uint256",
        "name": "propertyId",
        "type": "uint256"
      }
    ],
    "name": "getListings",
    "outputs": [
      {
        "components": [
          {
            "internalType": "address",
            "name": "seller",
            "type": "address"
          },
          {
            "internalType": "uint256",
            "name": "tokenAmount",
            "type": "uint256"
          },
          {
            "internalType": "uint256",
            "name": "pricePerToken",
            "type": "uint256"
          }
        ],
        "internalType": "struct RealEstateTokenFactory.Listing[]",
        "name": "",
        "type": "tuple[]"
      }
    ],
    "stateMutability": "view",
    "type": "function"
  },
  {
    "inputs": [],
    "name": "getPendingProperties",
    "outputs": [
      {
        "internalType": "uint256[]",
        "name": "propertyIds",
        "type": "uint256[]"
      },
      {
        "components": [
          {
            "internalType": "string",
            "name": "propertyAddress",
            "type": "string"
          },
          {
            "internalType": "uint256",
            "name": "value",
            "type": "uint256"
          },
          {
            "internalType": "address",
            "name": "originalOwner",
            "type": "address"
          },
          {
            "internalType": "string[]",
            "name": "propertyImageURLs",
            "type": "string[]"
          },
          {
            "internalType": "string[]",
            "name": "documentURLs",
            "type": "string[]"
          },
          {
            "internalType": "bool",
            "name": "approved",
            "type": "bool"
          },
          {
            "internalType": "bool",
            "name": "exists",
            "type": "bool"
          },
          {
            "internalType": "string",
            "name": "title",
            "type": "string"
          },
          {
            "internalType": "string",
            "name": "description",
            "type": "string"
          },
          {
            "internalType": "string",
            "name": "propertyType",
            "type": "string"
          },
          {
            "internalType": "string",
            "name": "apartmentType",
            "type": "string"
          },
          {
            "internalType": "uint256",
            "name": "bedrooms",
            "type": "uint256"
          },
          {
            "internalType": "uint256",
            "name": "bathrooms",
            "type": "uint256"
          },
          {
            "internalType": "uint256",
            "name": "area",
            "type": "uint256"
          },
          {
            "internalType": "uint256",
            "name": "yearBuilt",
            "type": "uint256"
          },
          {
            "internalType": "string",
            "name": "city",
            "type": "string"
          },
          {
            "internalType": "string",
            "name": "state",
            "type": "string"
          },
          {
            "internalType": "string",
            "name": "zipCode",
            "type": "string"
          },
          {
            "internalType": "string[]",
            "name": "amenities",
            "type": "string[]"
          }
        ],
        "internalType": "struct RealEstateTokenFactory.PendingProperty[]",
        "name": "propertiesList",
        "type": "tuple[]"
      }
    ],
    "stateMutability": "view",
    "type": "function"
  },
  {
    "inputs": [],
    "name": "getProperties",
    "outputs": [
      {
        "internalType": "string[]",
        "name": "propertyAddresses",
        "type": "string[]"
      },
      {
        "internalType": "uint256[]",
        "name": "values",
        "type": "uint256[]"
      },
      {
        "internalType": "address[]",
        "name": "tokenAddresses",
        "type": "address[]"
      },
      {
        "internalType": "string[][]",
        "name": "propertyImageURLsList",
        "type": "string[][]"
      },
      {
        "internalType": "string[][]",
        "name": "documentURLsList",
        "type": "string[][]"
      },
      {
        "internalType": "address[]",
        "name": "originalOwners",
        "type": "address[]"
      },
      {
        "internalType": "string[]",
        "name": "titles",
        "type": "string[]"
      },
      {
        "internalType": "string[]",
        "name": "descriptions",
        "type": "string[]"
      },
      {
        "internalType": "string[]",
        "name": "propertyTypes",
        "type": "string[]"
      },
      {
        "internalType": "string[]",
        "name": "apartmentTypes",
        "type": "string[]"
      },
      {
        "internalType": "uint256[]",
        "name": "bedroomsList",
        "type": "uint256[]"
      },
      {
        "internalType": "uint256[]",
        "name": "bathroomsList",
        "type": "uint256[]"
      },
      {
        "internalType": "uint256[]",
        "name": "areas",
        "type": "uint256[]"
      },
      {
        "internalType": "uint256[]",
        "name": "yearsBuilt",
        "type": "uint256[]"
      },
      {
        "internalType": "string[]",
        "name": "cities",
        "type": "string[]"
      },
      {
        "internalType": "string[]",
        "name": "states",
        "type": "string[]"
      },
      {
        "internalType": "string[]",
        "name": "zipCodes",
        "type": "string[]"
      },
      {
        "internalType": "string[][]",
        "name": "amenitiesList",
        "type": "string[][]"
      }
    ],
    "stateMutability": "view",
    "type": "function"
  },
  {
    "inputs": [
      {
        "internalType": "uint256",
        "name": "propertyId",
        "type": "uint256"
      },
      {
        "internalType": "uint256",
        "name": "tokenAmount",
        "type": "uint256"
      },
      {
        "internalType": "uint256",
        "name": "pricePerToken",
        "type": "uint256"
      }
    ],
    "name": "listForSale",
    "outputs": [],
    "stateMutability": "nonpayable",
    "type": "function"
  },
  {
    "inputs": [],
    "name": "nextPendingPropertyId",
    "outputs": [
      {
        "internalType": "uint256",
        "name": "",
        "type": "uint256"
      }
    ],
    "stateMutability": "view",
    "type": "function"
  },
  {
    "inputs": [],
    "name": "owner",
    "outputs": [
      {
        "internalType": "address",
        "name": "",
        "type": "address"
      }
    ],
    "stateMutability": "view",
    "type": "function"
  },
  {
    "inputs": [
      {
        "internalType": "uint256",
        "name": "",
        "type": "uint256"
      }
    ],
    "name": "pendingProperties",
    "outputs": [
      {
        "internalType": "string",
        "name": "propertyAddress",
        "type": "string"
      },
      {
        "internalType": "uint256",
        "name": "value",
        "type": "uint256"
      },
      {
        "internalType": "address",
        "name": "originalOwner",
        "type": "address"
      },
      {
        "internalType": "bool",
        "name": "approved",
        "type": "bool"
      },
      {
        "internalType": "bool",
        "name": "exists",
        "type": "bool"
      },
      {
        "internalType": "string",
        "name": "title",
        "type": "string"
      },
      {
        "internalType": "string",
        "name": "description",
        "type": "string"
      },
      {
        "internalType": "string",
        "name": "propertyType",
        "type": "string"
      },
      {
        "internalType": "string",
        "name": "apartmentType",
        "type": "string"
      },
      {
        "internalType": "uint256",
        "name": "bedrooms",
        "type": "uint256"
      },
      {
        "internalType": "uint256",
        "name": "bathrooms",
        "type": "uint256"
      },
      {
        "internalType": "uint256",
        "name": "area",
        "type": "uint256"
      },
      {
        "internalType": "uint256",
        "name": "yearBuilt",
        "type": "uint256"
      },
      {
        "internalType": "string",
        "name": "city",
        "type": "string"
      },
      {
        "internalType": "string",
        "name": "state",
        "type": "string"
      },
      {
        "internalType": "string",
        "name": "zipCode",
        "type": "string"
      }
    ],
    "stateMutability": "view",
    "type": "function"
  },
  {
    "inputs": [
      {
        "internalType": "uint256",
        "name": "",
        "type": "uint256"
      }
    ],
    "name": "properties",
    "outputs": [
      {
        "internalType": "string",
        "name": "propertyAddress",
        "type": "string"
      },
      {
        "internalType": "uint256",
        "name": "value",
        "type": "uint256"
      },
      {
        "internalType": "address",
        "name": "tokenAddress",
        "type": "address"
      },
      {
        "internalType": "address",
        "name": "originalOwner",
        "type": "address"
      },
      {
        "internalType": "string",
        "name": "title",
        "type": "string"
      },
      {
        "internalType": "string",
        "name": "description",
        "type": "string"
      },
      {
        "internalType": "string",
        "name": "propertyType",
        "type": "string"
      },
      {
        "internalType": "string",
        "name": "apartmentType",
        "type": "string"
      },
      {
        "internalType": "uint256",
        "name": "bedrooms",
        "type": "uint256"
      },
      {
        "internalType": "uint256",
        "name": "bathrooms",
        "type": "uint256"
      },
      {
        "internalType": "uint256",
        "name": "area",
        "type": "uint256"
      },
      {
        "internalType": "uint256",
        "name": "yearBuilt",
        "type": "uint256"
      },
      {
        "internalType": "string",
        "name": "city",
        "type": "string"
      },
      {
        "internalType": "string",
        "name": "state",
        "type": "string"
      },
      {
        "internalType": "string",
        "name": "zipCode",
        "type": "string"
      }
    ],
    "stateMutability": "view",
    "type": "function"
  },
  {
    "inputs": [
      {
        "internalType": "string",
        "name": "_propertyAddress",
        "type": "string"
      },
      {
        "internalType": "uint256",
        "name": "_valueUSD",
        "type": "uint256"
      },
      {
        "internalType": "string[]",
        "name": "_propertyImageURLs",
        "type": "string[]"
      },
      {
        "internalType": "string[]",
        "name": "_documentURLs",
        "type": "string[]"
      },
      {
        "internalType": "string",
        "name": "_title",
        "type": "string"
      },
      {
        "internalType": "string",
        "name": "_description",
        "type": "string"
      },
      {
        "internalType": "string",
        "name": "_propertyType",
        "type": "string"
      },
      {
        "internalType": "string",
        "name": "_apartmentType",
        "type": "string"
      },
      {
        "internalType": "uint256",
        "name": "_bedrooms",
        "type": "uint256"
      },
      {
        "internalType": "uint256",
        "name": "_bathrooms",
        "type": "uint256"
      },
      {
        "internalType": "uint256",
        "name": "_area",
        "type": "uint256"
      },
      {
        "internalType": "uint256",
        "name": "_yearBuilt",
        "type": "uint256"
      },
      {
        "internalType": "string",
        "name": "_city",
        "type": "string"
      },
      {
        "internalType": "string",
        "name": "_state",
        "type": "string"
      },
      {
        "internalType": "string",
        "name": "_zipCode",
        "type": "string"
      },
      {
        "internalType": "string[]",
        "name": "_amenities",
        "type": "string[]"
      }
    ],
    "name": "submitPropertyForApproval",
    "outputs": [],
    "stateMutability": "nonpayable",
    "type": "function"
  }
]